xontrib/init_ssh_agent.py
xontrib_init_ssh_agent-1.0.1.dist-info/LICENSE
xontrib_init_ssh_agent-1.0.1.dist-info/METADATA
xontrib_init_ssh_agent-1.0.1.dist-info/WHEEL
xontrib_init_ssh_agent-1.0.1.dist-info/top_level.txt
xontrib_init_ssh_agent-1.0.1.dist-info/RECORD
