Metadata-Version: 2.1
Name: xontrib-init-ssh-agent
Version: 1.0.1
Summary: Starts the ssh-agent and sources its PID and SOCK. Checks if xonsh already started an agent and updates the environment
Author-email: Bithive <bithive@bithive.space>
License: MIT License        
Project-URL: Homepage, https://github.com/theRealBithive/xontrib-init-ssh-agent
Project-URL: Documentation, https://github.com/theRealBithive/xontrib-init-ssh-agent/blob/master/README.md
Project-URL: Code, https://github.com/theRealBithive/xontrib-init-ssh-agent
Project-URL: Issue tracker, https://github.com/theRealBithive/xontrib-init-ssh-agent/issues
Platform: any
Classifier: Programming Language :: Python :: 3
Classifier: License :: OSI Approved :: MIT License
Classifier: Operating System :: OS Independent
Classifier: Topic :: System :: Shells
Classifier: Topic :: System :: System Shells
Classifier: Topic :: Terminals
Requires-Python: >=3.6
License-File: LICENSE
Requires-Dist: xonsh
Provides-Extra: dev
Requires-Dist: pytest (>=7.0) ; extra == 'dev'
